Workbook

Sheet Week1_Checklist
A1: Week 1 — Reporting Fundamentals
A3: Step | B3: Activity | C3: Evidence to Save | D3: Status
A4: 1 | B4: Excel advanced formulas | C4: Completed Formula_Practice sheet | D4: Not Started
A5: 2 | B5: Excel PivotTables | C5: 5 PivotTables answering stakeholder questions | D5: Not Started
A6: 3 | B6: Excel PivotCharts | C6: Charts for the 5 questions | D6: Not Started
A7: 4 | B7: Excel static report | C7: One-page dashboard/report | D7: Not Started
A8: 5 | B8: SQL Essential Training | C8: Saved SQL queries/screenshots | D8: Not Started
A9: 6 | B9: Power BI basics | C9: Basic .pbix file + screenshots | D9: Not Started
A10: 7 | B10: Week 1 reflection | C10: Short notes on what was learned | D10: Not Started

Sheet Pivot_Category_Sales
A2: Sales by Product Category
A3: Row Labels | B3: Sum of Sales
A4: Technology | B4: 375075.39
A5: Furniture | B5: 180651.51
A6: Office Supplies | B6: 9893.86
A7: Grand Total | B7: 565620.76
A30: Technology generates the highest sales at $375,075.39, followed by Furniture at $180,651.51. Office Supplies contributes the least at $9,893.86.

Sheet Pivot_Region_Sales
A3: Row Labels | B3: Sum of Sales
A4: North | B4: 184239.57
A5: South | B5: 128774.93
A6: East | B6: 127023.83
A7: West | B7: 125582.43
A8: Grand Total | B8: 565620.76
A30: Which region generates the highest revenue?
A31: North

Sheet Pivot_Subcategory_Profit
A3: Row Labels | B3: Sum of Profit
A4: Computers | B4: 32793.32
A5: Phones | B5: 18246.49
A6: Tables | B6: 11992.4
A7: Chairs | B7: 9045
A8: Machines | B8: 7793.2
A9: Bookcases | B9: 4269.69
A10: Furnishings | B10: 3529.9
A11: Accessories | B11: 2829.11
A12: Art | B12: 404.33
A13: Supplies | B13: 296.55
A14: Storage | B14: 290.54
A15: Paper | B15: 246.37
... A17: Grand Total | B17: 91879.19
A37: Which sub-category generates the highest profit?
A38: Computers

Sheet Pivot_Monthly_Sales
A3: Row Labels | B3: Sum of Sales
A4: 2025
A5: Jan | B5: 24428.26
A6: Feb | B6: 61619.71
A7: Mar | B7: 38376.7
A8: Apr | B8: 40676.71
A9: May | B9: 43129.07
A10: Jun | B10: 61064.89
A11: Jul | B11: 64826.01
A12: Aug | B12: 48022.71
A13: Sep | B13: 53065.32
A14: Oct | B14: 27859.79
A15: Nov | B15: 42778.61
A16: Dec | B16: 59772.98
A17: Grand Total | B17: 565620.76
A36: How are sales changing over time?
A37: Sales fluctuate throughout the year. The highest sales were recorded in July at $64,826.01, while the lowest sales were in October at $17,859.79. Sales increased strongly from May to July, declined in August and October, then recovered again in November and December.

Sheet Pivot_Segment_Sales
A3: Row Labels | B3: Sum of Sales
A4: Home Office | B4: 213454.27
A5: Corporate | B5: 186893.03
A6: Consumer | B6: 165273.46
A7: Grand Total | B7: 565620.76
A27: Which customer segment contributes the most sales?
A28: Home office

Sheet Dashboard
A2: SUPERSTORE SALES PERFORMANCE DASHBOARD
C3: Sales • Profit • Region • Category • Customer Analysis
H5: Total Sales | J5: Total Profit | L5: Top Category | N5: Top Region
H6: 565620.76 | J6: 91879.19 | L6: Technology | N6: North

Sheet Sales_Data
A1: Order ID | B1: Order Date | C1: Ship Date | D1: Customer ID | E1: Customer Name | F1: Segment | G1: Region | H1: State | I1: City | J1: Category | K1: Sub-Category | L1: Product Name | M1: Unit Price | N1: Quantity | O1: Discount | P1: Sales | Q1: Profit | S1: SUM | T1: AVERAGE | U1: COUNTIF | V1: SUMIF | W1: SUMIFS | X1: IF | Y1: XLOOKUP | Z1: TEXT | AA1: ROUND
A2: ORD-0001 | B2: 45729 | C2: 45735 | D2: C008 | E2: Lucas Martin | F2: Home Office | G2: North | H2: NT | I2: Darwin | J2: Office Supplies | K2: Binders | L2: Ring Binder | M2: 8.39 | N2: 2 | O2: 0.15 | P2: 14.25 | Q2: 2.66 | S2: =SUM(Sales_Data!P2:P501) -> 565620.76 | T2: =AVERAGE(Sales_Data!Q2:Q501) -> 183.75838 | U2: =COUNTIF(Sales_Data!G2:G501,"North") -> 139 | V2: =SUMIF(Sales_Data!J2:J501,"Technology",Sales_Data!P2:P501) -> 375075.39 | W2: =SUMIFS(Sales_Data!P2:P501,Sales_Data!J2:J501,"Technology",Sales_Data!G2:G501,"North") -> 126712.08 | X2: =IF(Sales_Data!Q2>0,"Profit","Loss") -> Profit | Y2: =_xlfn.XLOOKUP(Sales_Data!G2,Lookup_Data!A2:A5,Lookup_Data!B2:B5) -> Priya Shah | Z2: =TEXT(Sales_Data!B2,"mmmm") -> March | AA2: =ROUND(Sales_Data!P2,0) -> 14
A3: ORD-0002 | B3: 45966 | C3: 45967 | D3: C017 | E3: Emily Scott | F3: Consumer | G3: North | H3: NT | I3: Darwin | J3: Technology | K3: Accessories | L3: Wireless Mouse | M3: 46.35 | N3: 4 | O3: 0.15 | P3: 157.59 | Q3: 29.35
A4: ORD-0003 | B4: 45800 | C4: 45802 | D4: C011 | E4: Grace Thompson | F4: Consumer | G4: East | H4: NSW | I4: Sydney | J4: Furniture | K4: Furnishings | L4: Desk Lamp | M4: 62.88 | N4: 4 | O4: 0.2 | P4: 201.2 | Q4: 14.73
A5: ORD-0004 | B5: 45721 | C5: 45725 | D5: C018 | E5: William Green | F5: Corporate | G5: East | H5: NSW | I5: Wollongong | J5: Technology | K5: Computers | L5: Laptop | M5: 1390.02 | N5: 2 | O5: 0.1 | P5: 2502.04 | Q5: 518.32
A6: ORD-0005 | B6: 45996 | C6: 45998 | D6: C002 | E6: Noah Smith | F6: Consumer | G6: East | H6: NSW | I6: Wollongong | J6: Furniture | K6: Chairs | L6: Ergonomic Chair | M6: 417.71 | N6: 5 | O6: 0 | P6: 2088.57 | Q6: 556.86
A7: ORD-0006 | B7: 45765 | C7: 45771 | D7: C012 | E7: Leo Walker | F7: Corporate | G7: West | H7: WA | I7: Bunbury | J7: Technology | K7: Accessories | L7: USB-C Hub | M7: 76.11 | N7: 5 | O7: 0.15 | P7: 323.48 | Q7: 68.58
A8: ORD-0007 | B8: 45852 | C8: 45855 | D8: C015 | E8: Chloe King | F8: Home Office | G8: South | H8: SA | I8: Victor Harbor | J8: Technology | K8: Accessories | L8: Wireless Mouse | M8: 43.42 | N8: 4 | O8: 0.15 | P8: 147.62 | Q8: -15.08
A9: ORD-0008 | B9: 45819 | C9: 45821 | D9: C019 | E9: Zoe Baker | F9: Corporate | G9: East | H9: NSW | I9: Newcastle | J9: Technology | K9: Accessories | L9: Wireless Mouse | M9: 48.46 | N9: 8 | O9: 0.05 | P9: 368.31 | Q9: 77.61
A10: ORD-0009 | B10: 45957 | C10: 45961 | D10: C009 | E10: Olivia White | F10: Home Office | G10: South | H10: SA | I10: Adelaide | J10: Furniture | K10: Furnishings | L10: Monitor Stand | M10: 84.95 | N10: 7 | O10: 0 | P10: 594.63 | Q10: 178.02
A11: ORD-0010 | B11: 45963 | C11: 45964 | D11: C014 | E11: Henry Young | F11: Consumer | G11: North | H11: NT | I11: Darwin | J11: Technology | K11: Accessories | L11: Wireless Mouse | M11: 45.86 | N11: 7 | O11: 0.05 | P11: 304.99 | Q11: 50.94
A12: ORD-0011 | B12: 45986 | C12: 45989 | D12: C009 | E12: Olivia White | F12: Home Office | G12: North | H12: NT | I12: Katherine | J12: Technology | K12: Machines | L12: Printer | M12: 315.82 | N12: 2 | O12: 0 | P12: 631.65 | Q12: 103.23
A13: ORD-0012 | B13: 45985 | C13: 45990 | D13: C010 | E13: Jack Harris | F13: Consumer | G13: East | H13: NSW | I13: Wollongong | J13: Furniture | K13: Chairs | L13: Ergonomic Chair | M13: 380.17 | N13: 4 | O13: 0 | P13: 1520.66 | Q13: 137.45
A14: ORD-0013 | B14: 45843 | C14: 45850 | D14: C004 | E14: Liam Wilson | F14: Corporate | G14: North | H14: NT | I14: Katherine | J14: Office Supplies | K14: Paper | L14: A4 Copy Paper | M14: 10.94 | N14: 5 | O14: 0 | P14: 54.7 | Q14: 14.74
... A501: ORD-0500 | B501: 45997 | C501: 45999 | D501: C007 | E501: Amelia Thomas | F501: Corporate | G501: West | H501: WA | I501: Fremantle | J501: Office Supplies | K501: Supplies | L501: Desk Organiser | M501: 23.44 | N501: 8 | O501: 0 | P501: 187.53 | Q501: 27.41

Sheet Lookup_Data
A1: Region | B1: Regional Manager | D1: Segment | E1: Priority
A2: North | B2: Priya Shah | D2: Consumer | E2: Standard
A3: South | B3: Daniel Lee | D3: Corporate | E3: High
A4: East | B4: Emma Jones | D4: Home Office | E4: Medium
A5: West | B5: Michael Chen

Sheet Formula_Practice
A1: Excel Advanced Formulas Practice
A3: Task | B3: Skill | C3: Instruction | D3: Example/Hint | E3: Your Result | F3: Expected Result
A4: 1 | B4: SUM | C4: Calculate total Sales from Sales_Data. | D4: =SUM(Sales_Data!P2:P501) -> 565620.76 | F4: =SUM(Sales_Data!P2:P501) -> 565620.76
A5: 2 | B5: AVERAGE | C5: Calculate average Profit. | D5: =AVERAGE(Sales_Data!Q2:Q501) -> 183.75838 | F5: =AVERAGE(Sales_Data!Q2:Q501) -> 183.75838
A6: 3 | B6: COUNTIF | C6: Count orders in the "North" region. | D6: =COUNTIF(Sales_Data!G2:G501,"North") -> 139 | F6: =COUNTIF(Sales_Data!G2:G501,"North") -> 139
A7: 4 | B7: SUMIF | C7: Calculate Sales for "Technology". | D7: =SUMIF(Sales_Data!J2:J501,"Technology",Sales_Data!P2:P501) -> 375075.39 | F7: =SUMIF(Sales_Data!J2:J501,"Technology",Sales_Data!P2:P501) -> 375075.39
A8: 5 | B8: SUMIFS | C8: Calculate Technology Sales in the North region. | D8: =SUMIFS(Sales_Data!P2:P501,Sales_Data!J2:J501,"Technology",Sales_Data!G2:G501,"North") -> 126712.08 | F8: =SUMIFS(Sales_Data!P2:P501,Sales_Data!J2:J501,"Technology",Sales_Data!G2:G501,"North") -> 126712.08
A9: 6 | B9: IF | C9: Classify first order as Profit or Loss based on Profit value. | D9: =IF(Sales_Data!Q2>0,"Profit","Loss") -> Profit | F9: =IF(Sales_Data!Q2>0,"Profit","Loss") -> Profit
A10: 7 | B10: XLOOKUP | C10: Return the regional manager for the first order. | D10: =_xlfn.XLOOKUP(Sales_Data!G2,Lookup_Data!A2:A5,Lookup_Data!B2:B5) -> Priya Shah | F10: =_xlfn.XLOOKUP(Sales_Data!G2,Lookup_Data!A2:A5,Lookup_Data!B2:B5) -> Priya Shah
A11: 8 | B11: TEXT | C11: Return the month name for the first order date. | D11: =TEXT(Sales_Data!B2,"mmmm") -> March | F11: =TEXT(Sales_Data!B2,"mmmm") -> March
A12: 9 | B12: ROUND | C12: Round the first order Sales to the nearest whole number. | D12: =ROUND(Sales_Data!P2,0) -> 14 | F12: =ROUND(Sales_Data!P2,0) -> 14

Sheet Stakeholder_Questions
A1: Final Excel Report — 5 Stakeholder Questions
A3: # | B3: Stakeholder Question | C3: PivotTable Fields | D3: Recommended Chart | E3: Completed?
A4: 1 | B4: Which product category generates the highest sales? | C4: Rows: Category | Values: Sum of Sales | D4: Clustered Column | E4: Yes
A5: 2 | B5: Which region generates the highest revenue? | C5: Rows: Region | Values: Sum of Sales | D5: Bar Chart | E5: No
A6: 3 | B6: Which sub-category generates the highest profit? | C6: Rows: Sub-Category | Values: Sum of Profit | D6: Column Chart | E6: No
A7: 4 | B7: How are sales changing over time? | C7: Rows: Order Date (group by Month) | Values: Sum of Sales | D7: Line Chart | E7: No
A8: 5 | B8: Which customer segment contributes the most sales? | C8: Rows: Segment | Values: Sum of Sales | D8: Doughnut or Column | E8: No

Sheet Week1_Notes
A1: Topic | B1: Your Notes
A2: Excel advanced formulas
A3: PivotTables
A4: PivotCharts
A5: Static Excel report
A6: SQL SELECT / WHERE
A7: SQL GROUP BY / aggregates
A8: SQL JOIN basics
A9: Power BI import / visuals
A10: Week 1 reflection
